<page>
    <title>دانلد کنوت</title>
    <ns>0</ns>
    <id>5841</id>
    <revision>
      <id>17729679</id>
      <parentid>17507725</parentid>
      <timestamp>2016-07-28T09:19:29Z</timestamp>
      <contributor>
        <username>Rezabot</username>
        <id>206089</id>
      </contributor>
      <minor />
      <comment>ربات [[وپ:رده همسنگ#۲۶|ردهٔ همسنگ (۲۶)]] +مرتب+تمیز (۱۱.۵ core): + [[رده:دانشمندان آمریکایی سده ۲۰ (میلادی)]]+[[رده:ریاضی‌دانان آمریکایی سده ۲۱ (میلاد...</comment>
      <model>wikitext</model>
      <format>text/x-wiki</format>
      <text xml:space="preserve">{{جدول اطلاعات دانشمند
|نام               = دانلد کنوث
|تصویر             = KnuthAtOpenContentAlliance.jpg
|عرض تصویر         =
|زیرنویس           =
|تاریخ تولد        = {{تولد و سن|۱۹۳۸|۱|۱۰}}
|زادگاه            = [[میلواکی]] , [[ویسکانسین]]
|تاریخ مرگ         =
|محل مرگ           =
|محل زندگی         =
|شهروند            =
|ملیت              = [[ایالات متحده آمریکا|آمریکایی]]
|تبار              =
|رشته فعالیت       = [[ریاضیات]]{{سخ}}[[علوم رایانه]]
|محل کار           = [[دانشگاه استنفورد]]
|فارغ‌التحصیل       = [[دانشگاه کیس وسترن رزرو]]{{سخ}}[[موسسه فناوری کالیفرنیا]]
|بنیاد گذار        =
|استاد راهنما      =
|دانشجویان دکتری وی=
|دلیل شهرت         = [[هنر برنامه‌نویسی رایانه]]{{سخ}}[[تک]]{{سخ}}[[فراقلم]]{{سخ}}[[الگوریتم تطابق رشته با زمان خطی]]{{سخ}}MMIX
|تأثیرات           =
|جوایز             = [[جایزه تورینگ]] (۱۹۷۴){{-}} [[مدال فرانکلین]] (۱۹۸۸){{-}} [[نشان فارادی]] (۲۰۱۱)
|دین               =
|پانویس            =
|امضا              =
}}

'''دانلد اروین کنوث''' {{انگلیسی|Donald Ervin Knuth}} (زاده [[۱۰ ژانویه]]، [[۱۹۳۸ (میلادی)|۱۹۳۸]]) دانشمند علوم [[رایانه]] و استاد افتخاری در [[دانشگاه استانفورد]] در [[ایالت کالیفورنیا]]ی آمریکا است.

شهرت کنوث بیش از هر چیز مربوط به نگارش مجموعه کتاب‌های ''[[هنر برنامه‌نویسی رایانه]]'' است که یکی از گرانبهاترین مراجع در زمینه علوم رایانه به‌شمار می‌رود.

او عملاً پایه‌گذار رشته [[آنالیز الگوریتم‌ها]] است و سهم فراوانی در گسترش مبانی نظری شاخه‌های گوناگون علوم رایانه داشته است. وی همچنین طراح سیستم [[حروف‌چینی]] [[تک]] TeX و سامانه طراحی حروف [[فراقلم]] (Metafont) و مطرح کننده مفهوم [[برنامه‌نویسی ادیبانه]] است.

== پژوهش‌ها و فعالیت‌های دانشگاهی ==
زادگاه وی شهر میلواکی در [[ویسکانسین]] است و دوره‌های کارشناسی و کارشناسی ارشد در رشته ریاضیات را تا [[۱۹۶۰ (میلادی)|۱۹۶۰]] در موسسه [[فناوری]] کیس گذراند.

[[پرونده:Donald Knuth DSC00624.jpg|بندانگشتی||دانلد کنوث]]

در [[۱۹۶۳ (میلادی)|۱۹۶۳]] دکترای خود در ریاضیات را از موسسه فناوری کالیفرنیا دریافت کرد؛ همان جا بود که به مقام استادی رسید و کار بر روی «[[هنر برنامه‌نویسی رایانه]]» را آغاز کرد، کتابی که قرار است در هفت جلد منتشر شود. او در [[۱۹۶۸ (میلادی)|۱۹۶۸]]، سالی که به دانشگاه استانفورد پیوست، نخستین جلد این مجموعه را منتشر کرد.

[[پرونده:Jacob Appelbaum and Donald Knuth.jpg|thumb]]
در [[۱۹۷۱ (میلادی)|۱۹۷۱]] کنوث برنده نخستین دوره [[جایزه گریس موری هاپر]] شد. او جوایز بسیار دیگری را نیز به خود اختصاص داده است از جمله [[جایزه تورینگ]]، [[نشان ملی علوم]]، [[نشان جان فون‌نویمان]] و [[جایزه کیوتو]]. پس از انتشار سومین جلد مجوعه‌اش در سال [[۱۹۷۶ (میلادی)|۱۹۷۶]] و در اثر نارضایتی از محدودیت‌های ابزارهای رایج حروف‌چینی و نشر به پیاده‌سازی سامانه‌های تک و فراقلم مشغول شد.

برای قدردانی از فعالیت‌ها و کمک‌های کنوث به علوم رایانه، لقب منحصربه‌فرد «استاد در هنر برنامه‌نویسی رایانه» در سال [[۱۹۹۰ (میلادی)|۱۹۹۰]] به وی اهدا شد. این لقب از آن پس «استاد افتخاری در هنر برنامه‌نویسی رایانه» خوانده می‌شود. (Professor Emeritus of the Art of Computer Programming)

او در [[۱۹۹۲ (میلادی)|۱۹۹۲]] به عضویت [[فرهنگستان علوم فرانسه]] در آمد و همان سال نیز برای کار روی «هنر برنامه‌نویسی رایانه»
پژوهشهای معمول و تدریس در دانشگاه استانفورد را رها کرد. در سال [[۲۰۰۳ (میلادی)|۲۰۰۳]] وی به اعضای [[انجمن سلطنتی لندن]] پیوست.

سال [[۲۰۰۴ (میلادی)|۲۰۰۴]]، سال بازچاپ سه جلد نخست مجوعه‌اش بود در حالی که کنوث هم اکنون روی جلد چهارم کار می‌کند و به طور مرتب بخش‌هایی از آن را روی وب‌گاه شخصی‌اش منتشر می‌کند. هم‌زمان، کنوث، چندین بار در سال، سخنرانی‌هایی غیر رسمی در دانشگاه استانفورد ارائه می‌دهد که آنها را «تعمقی در رایانه» می‌نامد.

== نکات کوچک‌تر ==
کنوث برنامه‌نویس مشهوری است که به شوخ‌طبعی‌های بازیگوشانه‌اش معروف است:
* او به هرکسی که در کتاب‌هایش اشتباه یا هر ایراد چاپی پیدا کند دو دلار و پنجاه و شش سنت (۲٫۵۶) مژدگانی می‌دهد چون ''"۲۵۶ سنت برابر یک دلار در مبنای شانزده است."'' (این جایزه برای ایرادات کتاب "۳:۱۶ درک متون کتاب مقدس" سه دلار و شانزده سنت است)
* شماره نسخه‌های [[نرم‌افزار]] تک او به عدد π میل می‌کند، یعنی شماره نسخه‌ها با ترتیب ۳، ۳٫۱، ۳٫۱۴ و مانند آن افزایش پیدا می‌کند. شماره نسخه‌های فراقلم به عدد e میل می‌کند.
* او یک بار به استفاده کنندگان نرم‌افزارش هشدار داد: "مراقب اشکالات کد این برنامه باشید؛ من نشان داده‌ام که برنامه درست کار می‌کند، اما آن را امتحان نکرده‌ام."
* علاوه بر نوشته‌هایش در زمینه علوم رایانه، کنوث هم‌چنین نویسنده[http://www.amazon.com/exec/obidos/tg/detail/-/0895792524/qid=1121940918/sr=8-1/ref=pd_bbs_1/104-8679232-4799132?v=glance&amp;s=books&amp;n=507846 ''۳:۱۶ روشنگری متون انجیل''] که در آن او کتاب مقدس را طی فرایند «نمونه برداری تصادفی طبقه‌بندی شده» بررسی می‌کند، یا به طور دقیق‌تر، او هر بند شماره ۱۶ از هر بخش با شماره ۳ هر کتاب را مطالعه می‌کند. او هر بند را با نمونه خطاطی شده آن همراه کرده است، که حاصل تلاش داوطلبانه گروهی از خوشنویسان زیر نظر [[هرمان زاف]] است.
* کنوث نخستین نوشتار علمی‌اش به نام «سامانه پاتچبی (Potrzebie) برای وزن‌ها و دیگر میزان‌ها» را در یک مجله مدرسه‌ای در [[۱۹۵۷ (میلادی)|۱۹۵۷]] منتشر کرد و در آن واحد طول را ضخامت شماره ۲۶ مجله MAD تعریف کرد و نام واحد نیرو را نیز "whatmeworry" ("نگرانم می‌کنه") نامید. مجله MAD مقاله را خرید و در نسخه [[ژوئن]] [[۱۹۵۷ (میلادی)|۱۹۵۷]] خود منتشر کرد.

== زندگی شخصی ==
کنوت که [[لوتریانیسم|لوتری]] است علاوه بر مکتوبات علوم کامپیوتری، نویسندهٔ کتاب ''3:16 Bible Texts Illuminated'' است،&lt;ref&gt;{{Citation | last = Knuth| first = Donald Ervin | title = 3:16: Bible texts illuminated | year = 1991 | place = Madison, [[ویسکانسین|Wisconsin]] | publisher = A-R Eds | isbn = 978-0-89579-252-5}}&lt;/ref&gt; که در آن انجیل را توسط فرایندی [[systematic sampling]] بررسی می‌کند، مشخصاً تحلیلی از فصل ۳، آیه ۱۶ هر کتاب ارائه می‌کند. به همراه هر آیه یک اثر هنری خطاطی از گروهی از خطاطان آمده است.

از سرگرمی‌های کنوث موسیقی و به ویژه نواختن ارگ کلیسا است. او یک ارغنون لوله‌ای در منزل خود نصب کرده است و با این همه داشتن هر استعدادی در نواختن این ساز را انکار می‌کند. او از پست الکترونیکی استفاده نمی‌کند، زیرا به گفته خودش آن را از [[۱۹۷۵ (میلادی)|۱۹۷۵]] تا اول [[ژانویه]] [[۱۹۹۰ (میلادی)|۱۹۹۰]] به کار برده که برای یک عمر کافی است. در عوض مکاتبه فلّه‌ای را موثرتر می‌داند یعنی استفاده از پست سنتی هر چند ماه یکبار.

همسر او جیل کنوث است که کتابی با عنوان ''بیرق‌های بی‌نوشته'' در مورد طرح بیرق‌های متفاوتی که در مراسم مذهبی مسیحیان در کلیسا استفاده می‌شود را در سال [[۱۹۸۶ (میلادی)|۱۹۸۶]] منتشر کرده است. این زوج دو فرزند دارند.

== جستارهای وابسته ==
* [[برنامه نویسی ادیبانه]]
* [[تولید اعداد تصادفی در رایانه]]
{{-}}
== منابع ==
{{پانویس}}
* {{یادکرد وب| نشانی = http://en.wikipedia.org/wiki/Donald_Knuth| عنوان = منبع جعبه زندگی‌نامه| نویسنده = | تاریخ بازدید = ۱۱ فوریه ۲۰۰۸| تاریخ = | ناشر = ویکی‌پدیای انگلیسی| صفحه = | زبان = انگلیسی}}

== پیوند به بیرون ==
* [http://www-cs-faculty.stanford.edu/~knuth/ وب‌گاه استنفورد برای دانلد کنوث]
* [http://www-gap.dcs.st-and.ac.uk/~history/Mathematicians/Knuth.html زندگینامه مفصل کنوث]
* [http://www.softpanorama.org/People/Knuth/index.shtml دونالد کنوث، لئونارد اویلر علوم رایانه]
* [http://scpd.stanford.edu/knuth/ ویدئوی سخنرانی‌های دانلد کنوث]
&lt;/div&gt;

{{برندگان جایزه تورینگ}}
{{مستند کردن}}
{{برندگان نشان ملی دانش}}

{{ترتیب‌پیش‌فرض:کنوث، دانلد}}

[[رده:دانلد کنوت]]
[[رده:آلمانی‌تبارهای اهل ایالات متحده آمریکا]]
[[رده:استادان دانشگاه استنفورد]]
[[رده:استادان دانشگاه اهل آمریکا]]
[[رده:اعضای خارجی انجمن سلطنتی]]
[[رده:اعضای خارجی فرهنگستان علوم روسیه]]
[[رده:اعضای فرهنگستان علوم فرانسه]]
[[رده:اعضای فرهنگستان ملی دانش آمریکا]]
[[رده:اعضای فرهنگستان ملی مهندسی آمریکا]]
[[رده:افراد زنده]]
[[رده:اهالی میلواکی، ویسکانسین]]
[[رده:برنامه‌نویسان رایانه آمریکایی]]
[[رده:برنامه‌نویسان نرم‌افزار آزاد]]
[[رده:برندگان جایزه تورینگ]]
[[رده:برندگان نشان ملی دانش]]
[[رده:پیشگامان رایانه]]
[[رده:دانشمندان آمریکایی سده ۲۰ (میلادی)]]
[[رده:دانشمندان رایانه اهل ایالات متحده آمریکا]]
[[رده:دانش‌آموختگان انستیتوی فناوری کالیفرنیا]]
[[رده:دانش‌آموختگان دانشگاه کیس وسترن رزرو]]
[[رده:دریافت‌کنندگان جایزه گوگنهایم]]
[[رده:ریاضی‌دانان آمریکایی سده ۲۰ (میلادی)]]
[[رده:ریاضی‌دانان آمریکایی سده ۲۱ (میلادی)]]
[[رده:ریاضی‌دانان اهل ایالات متحده آمریکا]]
[[رده:ریاضی‌دانان سده ۲۰ (میلادی)]]
[[رده:زادگان ۱۹۳۸ (میلادی)]]
[[رده:لوتری‌های اهل ایالات متحده آمریکا]]
[[رده:نویسندگان اهل کالیفرنیا]]
[[رده:نویسندگان فناوری اهل ایالات متحده آمریکا]]
[[رده:طراحان زبان‌های برنامه‌نویسی]]</text>
      <sha1>hjvobput2qdtjnit7hrkkjzy5kjj5ge</sha1>
    </revision>
  </page>
  