<page>
    <title>دستگاه ادراری تناسلی (ابهام‌زدایی)</title>
    <ns>0</ns>
    <id>3324</id>
    <revision>
      <id>12999083</id>
      <parentid>12999059</parentid>
      <timestamp>2014-07-31T08:18:22Z</timestamp>
      <contributor>
        <username>Reza luke</username>
        <id>56083</id>
      </contributor>
      <model>wikitext</model>
      <format>text/x-wiki</format>
      <text xml:space="preserve">[[دستگاه ادراری تناسلی]] مجموع دو دستگاه ادراری و تناسلی است. در [[واژگان کالبدشناسی]] ممکن است به یکی از موارد زیر اشاره داشته باشد:

* [[دستگاه تناسلی]]
* [[دستگاه ادراری]]
{{ابهام‌زدایی}}</text>
      <sha1>tbxwxe1bpx5tao79ajsnxxokoxxa06y</sha1>
    </revision>
  </page>
  