<page>
    <title>خلم</title>
    <ns>0</ns>
    <id>6200</id>
    <revision>
      <id>13385385</id>
      <parentid>9593911</parentid>
      <timestamp>2014-10-05T21:35:14Z</timestamp>
      <contributor>
        <username>Rezabot</username>
        <id>206089</id>
      </contributor>
      <minor />
      <comment>[[وپ:دار|ربات:انتقال رده]] &gt; [[:رده:شهرهای افغانستان]] به [[:رده:شهرها در افغانستان]]</comment>
      <model>wikitext</model>
      <format>text/x-wiki</format>
      <text xml:space="preserve">{{coord|36|41|0|N|67|41|0|E|type:city_region:AF|display=title}}
{{جعبه شهر افغانستان
|نام‌رسمی=خلم 
|عرض‌جغرافیایی =
|طول‌جغرافیایی =
|تصویر= 
|اندازه‌تصویر= 
|برچسب‌تصویر= 
|ولایت=بلخ  
|ولسوالی=
|علاقه‌داری=  
|نام‌محلی=
|نام‌های‌قدیمی=
|سال‌شهرشدن=  
|جمعیت =
|رشدجمعیت=
|تراکم‌جمعیت=
|زبان=
|مذهب=
|مساحت=
|ارتفاع=
|میانگین‌دما=
|میانگین‌بارش‌سالانه=
|شمارروزهای‌یخبندان=
|شهردار=
|ره‌آورد=
|پیش‌شماره=
|وب‌گاه=
|جمله‌خوشامد=
|پانویس=
}}

'''خُلم''' نام یک شهر و یکی از بخش‌ها (ولسوالی‌ها)ی [[استان بلخ]] [[افغانستان]] است. این شهر از دیرینگی بسیار زیادی برخوردار است.
خلم در زمانه های بسیار کهن به همین نام مسمی بوده است که پسان ها در زمان حکومت یونان باختری با بنای جدید بر این شهر به نام یورکتیدیا یاد شد پس از آن در قرن ۱۷ میلادی در زمان میر قلیچ علی بیگ نام ترکی به خود گرفت و به تاشقرغان شهرت یافت.&lt;ref&gt;خلم(تاشقرغان) در درازنای تاریخ نوشته قاضی عبدالحی تاشقرغانی به همکاری انجنیر فضل احمد طغیان چاپ اول مورخ ۱۳۸۷ مطبعه اسد دانش کابل صفحات ۱۶۴ و۱&lt;/ref&gt;

== منابع ==
{{پانویس}}
{{افغانستان-خرد}}

[[رده:مناطق مسکونی در ولایت بلخ]]
[[رده:شهرها در افغانستان]]</text>
      <sha1>0jw77ikbmum9lavusxt68yf67ldrp7y</sha1>
    </revision>
  </page>
  