<page>
    <title>جاز فیوژن</title>
    <ns>0</ns>
    <id>6415</id>
    <revision>
      <id>17894654</id>
      <parentid>17894653</parentid>
      <timestamp>2016-08-14T15:23:27Z</timestamp>
      <contributor>
        <username>Wikimostafa</username>
        <id>385898</id>
      </contributor>
      <minor />
      <model>wikitext</model>
      <format>text/x-wiki</format>
      <text xml:space="preserve">{{منبع|تاریخ=اکتبر ۲۰۱۵}}
{{Infobox music genre
|name=جاز فیوژن
|color=white
|bgcolor=black
|image=
|image_size=
|caption=
|stylistic_origins={{hlist|[[جاز]]|[[موسیقی راک]]|[[فانک]]|[[موسیقی الکترونیک]]|[[بلوز]]|[[موسیقی سایکدلیک]]|[[موسیقی کلاسیک]]}}
|cultural_origins=اواخر دهه ۱۹۶۰، ایالات متحده
|instruments={{hlist|[[گیتار الکتریک]]|[[پیانو]]|[[پیانو الکتریک]]|[[درام (ساز)|درام]]|[[ساکسیفون]]|[[ترومپت]]|[[کیبورد الکترونیک]]|[[گیتار بیس]]|خوانندگی}}
|popularity=زیاد، به‌خصوص در دهه ۱۹۷۰
|derivatives={{hlist|[[جاز نرم]]|[[اسید جاز]]|[[پانک جاز]]|[[جاز فیوژن]]|[[پراگرسیو راک]]|[[کراوت‌راک]]}}
|other_topics=*[[List of jazz fusion musicians]]
*[[سول جاز]]
*[[جاز فانک]]
*[[جاز رپ]]
*[[نیو جاز]]}}
{{گسترش}}
'''جاز تلفیقی'''، '''جاز فیوژن''' یا '''جَز فیوژن''' {{انگلیسی|Jazz fusion}} نام سبکی از [[جاز]] است که در آن سعی در تلفیق بعضی انواع دیگر موسیقی ([[راک]]، [[ریتم اند بلوز]] و ...) با تکنیک‌های جاز می‌شود.
{{موسیقی-خرد}}
{{جاز}}
{{موسیقی راک}}
[[رده:ژانرهای موسیقی تلفیقی]]
[[رده:ژانرهای موسیقی جاز]]
[[رده:سبک‌های موسیقی راک]]</text>
      <sha1>56osb66szqaetg1nobr7pjurpt2xrke</sha1>
    </revision>
  </page>
  