<page>
    <title>زبان نشانه‌گذاری ابرمتنی</title>
    <ns>0</ns>
    <id>7095</id>
    <redirect title="اچ‌تی‌ام‌ال" />
    <revision>
      <id>62334</id>
      <parentid>25652</parentid>
      <timestamp>2005-11-10T05:59:26Z</timestamp>
      <contributor>
        <username>Saki-bot~fawiki</username>
        <id>2236</id>
      </contributor>
      <minor />
      <comment>Robot: Fixing double redirect</comment>
      <model>wikitext</model>
      <format>text/x-wiki</format>
      <text xml:space="preserve">#REDIRECT [[اچ‌تی‌ام‌ال]]</text>
      <sha1>gi6dnu5bjmuymom4dop8q9s3tb8ed5q</sha1>
    </revision>
  </page>
  