<page>
    <title>دریای عربی</title>
    <ns>0</ns>
    <id>3670</id>
    <redirect title="دریای عرب" />
    <revision>
      <id>23043</id>
      <parentid>8821</parentid>
      <timestamp>2004-12-24T12:02:40Z</timestamp>
      <contributor>
        <username>Masoud</username>
        <id>5</id>
      </contributor>
      <minor />
      <comment>(انتقال به دریای عرب)</comment>
      <model>wikitext</model>
      <format>text/x-wiki</format>
      <text xml:space="preserve">#REDIRECT [[دریای عرب]]</text>
      <sha1>mqb2gvleeeytcbijjw5zoq5b5h2xd81</sha1>
    </revision>
  </page>
  