<page>
    <title>استان ملطیه</title>
    <ns>0</ns>
    <id>4222</id>
    <revision>
      <id>16560137</id>
      <parentid>16560134</parentid>
      <timestamp>2016-02-05T12:07:04Z</timestamp>
      <contributor>
        <username>Arian Ar</username>
        <id>485937</id>
      </contributor>
      <minor />
      <comment>ویرایش [[Special:Contributions/89.196.204.203|89.196.204.203]] ([[User talk:89.196.204.203|بحث]]) به آخرین تغییری که [[User:KasparBot|KasparBot]] انجام داده بود واگردانده شد</comment>
      <model>wikitext</model>
      <format>text/x-wiki</format>
      <text xml:space="preserve">{{Infobox settlement
&lt;!-- See Template:Infobox settlement for additional fields and descriptions --&gt;
| name                    = استان ملطیه
| native_name             = Malatya ili
| native_name_lang        = &lt;!-- ISO 639-2 code e.g. "fr" for French. If more than one, use {{lang}} instead --&gt;
| settlement_type         =  [[فهرست استان‌های ترکیه|استان]]
| image_skyline           = 
| image_alt               = 
| image_caption           = 
| image_flag              = 
| flag_alt                = 
| image_seal              = 
| seal_alt                = 
| image_shield            = 
| shield_alt              = 
| nickname                = 
| motto                   = 
| image_map               = Malatya Turkey Provinces locator.gif
| map_alt                 = 
| map_caption             = 
| image_map1              = Malatya districts.png 
| mapsize1                =
| map_alt1                =
| map_caption1            = 
| pushpin_map             = 
| pushpin_label_position  = 
| pushpin_map_alt         = 
| pushpin_map_caption     = 
| latd  = 38 |latm  = 29 |lats  = 03 |latNS  = N
| longd = 38 |longm = 08 |longs = 11 |longEW = E
| coor_pinpoint           = 
| coordinates_type        = 
| coordinates_display     = inline,title
| coordinates_footnotes   = 
| subdivision_type        = [[فهرست کشورهای جهان|کشور]]
| subdivision_name        = {{TUR}}
| subdivision_type1       = ناحیه
| subdivision_name1       = [[ناحیه آناتولی شرقی|آناتولی شرقی]]
| subdivision_type2       = مرکز 
| subdivision_name2       = [[ملطیه]]
| subdivision_type3       = 
| subdivision_name3       = 
| established_title       = 
| established_date        = 
| founder                 = 
| seat_type               = 
| seat                    = 
| government_footnotes    = 
| leader_party            = 
| leader_title            =  فرماندار 
| leader_name             = Ulvi Saran
| unit_pref               = Metric&lt;!-- or US or UK --&gt;
| area_footnotes          = 
| area_total_km2          = 12,313 
| area_land_km2           = 
| area_water_km2          = 
| area_water_percent      = 
| area_note               = 
| elevation_footnotes     = 
| elevation_m             = 
| population_footnotes    = 
| population_total        = 740,643
| population_as_of        = ۲۰۱۰
| population_density_km2  = auto
| population_demonym      = 
| population_note         = 
| timezone1               = 
| utc_offset1             = 
| timezone1_DST           = 
| utc_offset1_DST         = 
| postal_code_type        =  [[کد پستی]]
| postal_code             = 
| area_code_type          = 
| area_code               = ۰۴۲۲  
| iso_code                = 
| website                 = {{URL|http://www.malatya.gov.tr/}} 
| footnotes               = 
}}

'''استان مَلَطیه''' یا '''ملاطیه''' {{به ترکی|Malatya ili}} نام یکی از استان‌های [[ترکیه]] واقع در منطقهٔ [[ناحیه آناتولی شرقی]] است.

مرکز این استان شهر [[ملطیه]] است.

== شهرستان‌ها ==
* [[آقچه‌داغ]] Akçadağ
* [[عرب‌گیر]] Arapgir
* [[ارگوان]] Arguvan
* [[بطال‌غازی|بَطّال‌غازی]]&lt;ref&gt;[http://www.encyclopaediaislamica.com/madkhal2.php?sid=1425 Battalgazi]&lt;/ref&gt;
* [[دارنده]] Darende
* [[دوغان‌شهر]] Doğanşehir
* [[دوغان‌یول]] Doğanyol
* [[حکیم‌خان]] Hekimhan
* [[قلعه (ملطیه)|قلعه]] Kale
* [[کولونجاک]] Kuluncak
* '''[[ملطیه]]''' Malatya
* [[پوتورگه]] Pütürge
* [[یازی‌خان]] Yazıhan
* [[یشیل‌یورت (ملطیه)|یشیل‌یورت]] Yeşilyurt
[[پرونده:Malatya Turkey Provinces locator.jpg|بندانگشتی|راست|280px|محل استان ملطیه]]

{{-}}
== منابع ==
{{ویکی‌انبار-رده|Malatya Province}}
* [//en.wikipedia.org/w/index.php?title=Malatya_Province&amp;oldid=310508228 Wikipedia contributors, "Malatya Province," Wikipedia, The Free Encyclopedia, (accessed August 28, 2009).]
{{پانویس}}
{{استان‌های ترکیه}}
{{داده‌های کتابخانه‌ای}}

{{ترکیه-خرد}}

[[رده:استان ملطیه]]
[[رده:استان‌های ترکیه|ملاطیه]]
[[رده:کردستان]]</text>
      <sha1>j5p4rhrfuhjewkhx3rx6bu44ordul6m</sha1>
    </revision>
  </page>
  