<page>
    <title>فلوندر</title>
    <ns>0</ns>
    <id>4867</id>
    <redirect title="کفشک (ماهی)" />
    <revision>
      <id>13233723</id>
      <parentid>23899</parentid>
      <timestamp>2014-09-06T01:49:34Z</timestamp>
      <contributor>
        <username>Xqbot</username>
        <id>113935</id>
      </contributor>
      <minor />
      <comment>ربات: اصلاح تغییرمسیر دوتایی به [[کفشک (ماهی)]]</comment>
      <model>wikitext</model>
      <format>text/x-wiki</format>
      <text xml:space="preserve">#تغییر_مسیر [[کفشک (ماهی)]]</text>
      <sha1>r7avojmzi2c8mf4y5vhdf27t6ha9itm</sha1>
    </revision>
  </page>
  